sourcesquirrel/__init__.py
sourcesquirrel/classes/__init__.py
sourcesquirrel/classes/blockchain.py
sourcesquirrel/classes/collection.py
sourcesquirrel/classes/media_type.py
sourcesquirrel/classes/platform.py
sourcesquirrel/classes/release_type.py
sourcesquirrel/classes/serie.py
sourcesquirrel/constants/__init__.py
sourcesquirrel/constants/blockchains.py
sourcesquirrel/constants/cryptocurrencies.py
sourcesquirrel/constants/platforms.py
sourcesquirrel/constants/sources.py
sourcesquirrel/excel.py
sourcesquirrel/helpers.py
sourcesquirrel/integrations/__init__.py
sourcesquirrel/integrations/google/__init__.py
sourcesquirrel/integrations/google/drive.py
sourcesquirrel/prefabs/__init__.py
sourcesquirrel/prefabs/blockchains.py
sourcesquirrel/prefabs/platforms.py
sourcesquirrel/sot.py
sourcesquirrel/utils/__init__.py
sourcesquirrel/utils/cardano.py
sourcesquirrel/validators/__init__.py
sourcesquirrel/validators/algorand.py
sourcesquirrel/validators/cardano.py
sourcesquirrel/validators/evm.py
sourcesquirrel/validators/utils.py
bookio_sourcesquirrel-0.5.1.dist-info/WHEEL
bookio_sourcesquirrel-0.5.1.dist-info/METADATA
bookio_sourcesquirrel-0.5.1.dist-info/RECORD
