Metadata-Version: 2.1
Name: bookio-sourcesquirrel
Version: 0.5.1
Summary: Source of truth for book.io and stuff.io data
Home-page: https://github.com/book-io/sourcesquirrel
License: MIT
Keywords: book.io,stuff.io,blockchain,crypto,algorand,cardano,coinbase,ethereum,polygon
Author: Fede
Author-email: fede@book.io
Requires-Python: >=3.9,<4.0
Classifier: Intended Audience :: Developers
Classifier: License :: OSI Approved :: MIT License
Classifier: Programming Language :: Python :: 3
Classifier: Programming Language :: Python :: 3.9
Classifier: Programming Language :: Python :: 3.10
Classifier: Programming Language :: Python :: 3.11
Classifier: Programming Language :: Python :: 3.10
Classifier: Programming Language :: Python :: 3.11
Classifier: Programming Language :: Python :: 3.12
Classifier: Programming Language :: Python :: 3.8
Classifier: Programming Language :: Python :: 3.9
Requires-Dist: openpyxl (>=3.1.5,<4.0.0)
Requires-Dist: pydrive2 (>=1.21.3,<2.0.0)
Project-URL: Documentation, https://github.com/book-io/sourcesquirrel/blob/main/README.md
